<?xml version="1.0" encoding="UTF-8"?>
<data>
	<node>
		<sku><![CDATA[127641945]]></sku>
		<category><![CDATA[Bicycles>Mountain Bikes]]></category>
		<tags><![CDATA[For real mans!]]></tags>
		<title><![CDATA[Велосипед Orbea Alma 29 H20-Eagle M 2020]]></title>
		<price><![CDATA[40880]]></price>
		<color><![CDATA[Blue-Yellow]]></color>
		<size><![CDATA[M]]></size>
		<images><![CDATA[https://content2.rozetka.com.ua/goods/images/big/17503805.jpg]]></images>
		<class><![CDATA[mountin]]></class>
		<number_of_speeds><![CDATA[12]]></number_of_speeds>
		<max_speed><![CDATA[]]></max_speed>
		<wheel_diameter><![CDATA[29]]></wheel_diameter>
		<frame_material><![CDATA[Aluminum]]></frame_material>
		<brake_type><![CDATA[Disk hydraulic]]></brake_type>
	</node>
	<node>
		<sku><![CDATA[127641938]]></sku>
		<category><![CDATA[Bicycles>Mountain Bikes]]></category>
		<tags><![CDATA[For real mans!]]></tags>
		<title><![CDATA[Велосипед Orbea Alma 29 H20-Eagle M 2021]]></title>
		<price><![CDATA[40880]]></price>
		<color><![CDATA[Black]]></color>
		<size><![CDATA[M]]></size>
		<images><![CDATA[https://content1.rozetka.com.ua/goods/images/big/95540595.jpg ]]></images>
		<class><![CDATA[mountin]]></class>
		<number_of_speeds><![CDATA[12]]></number_of_speeds>
		<max_speed><![CDATA[]]></max_speed>
		<wheel_diameter><![CDATA[29]]></wheel_diameter>
		<frame_material><![CDATA[Aluminum]]></frame_material>
		<brake_type><![CDATA[Disk hydraulic]]></brake_type>
	</node>
	<node>
		<sku><![CDATA[127641966]]></sku>
		<category><![CDATA[Bicycles>Mountain Bikes]]></category>
		<tags><![CDATA[For real mans!]]></tags>
		<title><![CDATA[Велосипед Orbea Alma 29 H20-Eagle M 2022]]></title>
		<price><![CDATA[40880]]></price>
		<color><![CDATA[Grey-Red]]></color>
		<size><![CDATA[M]]></size>
		<images><![CDATA[https://content.rozetka.com.ua/goods/images/big/17503778.jpg ]]></images>
		<class><![CDATA[mountin]]></class>
		<number_of_speeds><![CDATA[12]]></number_of_speeds>
		<max_speed><![CDATA[]]></max_speed>
		<wheel_diameter><![CDATA[29]]></wheel_diameter>
		<frame_material><![CDATA[Aluminum]]></frame_material>
		<brake_type><![CDATA[Disk hydraulic]]></brake_type>
	</node>
	<node>
		<sku><![CDATA[127641987]]></sku>
		<category><![CDATA[Bicycles>Mountain Bikes]]></category>
		<tags><![CDATA[For real mans!]]></tags>
		<title><![CDATA[Велосипед Orbea Alma 29 H20-Eagle M 2023]]></title>
		<price><![CDATA[40880]]></price>
		<color><![CDATA[Mint-Black]]></color>
		<size><![CDATA[M]]></size>
		<images><![CDATA[https://content2.rozetka.com.ua/goods/images/big/17503604.jpg ]]></images>
		<class><![CDATA[mountin]]></class>
		<number_of_speeds><![CDATA[12]]></number_of_speeds>
		<max_speed><![CDATA[]]></max_speed>
		<wheel_diameter><![CDATA[29]]></wheel_diameter>
		<frame_material><![CDATA[Aluminum]]></frame_material>
		<brake_type><![CDATA[Disk hydraulic]]></brake_type>
	</node>
	<node>
		<sku><![CDATA[285060078]]></sku>
		<category><![CDATA[Bicycles>Mountain Bikes]]></category>
		<tags><![CDATA[For real mans!]]></tags>
		<title><![CDATA[Велосипед Bergamont Revox 3 29" M/17"]]></title>
		<price><![CDATA[17640]]></price>
		<color><![CDATA[Silver]]></color>
		<size><![CDATA[17]]></size>
		<images><![CDATA[https://content1.rozetka.com.ua/goods/images/big/166242049.jpg ]]></images>
		<class><![CDATA[mountin]]></class>
		<number_of_speeds><![CDATA[24]]></number_of_speeds>
		<max_speed><![CDATA[]]></max_speed>
		<wheel_diameter><![CDATA[27.5]]></wheel_diameter>
		<frame_material><![CDATA[Aluminum]]></frame_material>
		<brake_type><![CDATA[Disk hydraulic]]></brake_type>
	</node>
	<node>
		<sku><![CDATA[285060108]]></sku>
		<category><![CDATA[Bicycles>Mountain Bikes]]></category>
		<tags><![CDATA[For real mans!]]></tags>
		<title><![CDATA[Велосипед Bergamont Revox 3 29" M/17"]]></title>
		<price><![CDATA[17641]]></price>
		<color><![CDATA[Yellow]]></color>
		<size><![CDATA[16]]></size>
		<images><![CDATA[https://content.rozetka.com.ua/goods/images/big/166243500.jpg ]]></images>
		<class><![CDATA[mountin]]></class>
		<number_of_speeds><![CDATA[24]]></number_of_speeds>
		<max_speed><![CDATA[]]></max_speed>
		<wheel_diameter><![CDATA[27.5]]></wheel_diameter>
		<frame_material><![CDATA[Aluminum]]></frame_material>
		<brake_type><![CDATA[Disk hydraulic]]></brake_type>
	</node>
	<node>
		<sku><![CDATA[285060158]]></sku>
		<category><![CDATA[Bicycles>Mountain Bikes]]></category>
		<tags><![CDATA[For real mans!]]></tags>
		<title><![CDATA[Велосипед Bergamont Revox 3 29" M/17"]]></title>
		<price><![CDATA[17642]]></price>
		<color><![CDATA[Bue]]></color>
		<size><![CDATA[17]]></size>
		<images><![CDATA[https://content1.rozetka.com.ua/goods/images/big/166244515.jpg ]]></images>
		<class><![CDATA[mountin]]></class>
		<number_of_speeds><![CDATA[24]]></number_of_speeds>
		<max_speed><![CDATA[]]></max_speed>
		<wheel_diameter><![CDATA[27.5]]></wheel_diameter>
		<frame_material><![CDATA[Aluminum]]></frame_material>
		<brake_type><![CDATA[Disk hydraulic]]></brake_type>
	</node>
	<node>
		<sku><![CDATA[249473466]]></sku>
		<category><![CDATA[Bicycles>Mountain Bikes]]></category>
		<tags><![CDATA[For real mans!]]></tags>
		<title><![CDATA[Велосипед Orbea Alma H10-Eagle 29 XL 2021]]></title>
		<price><![CDATA[49756]]></price>
		<color><![CDATA[Ice Green]]></color>
		<size><![CDATA[XL]]></size>
		<images><![CDATA[https://content1.rozetka.com.ua/goods/images/big/146235069.jpg ]]></images>
		<class><![CDATA[mountin]]></class>
		<number_of_speeds><![CDATA[12]]></number_of_speeds>
		<max_speed><![CDATA[]]></max_speed>
		<wheel_diameter><![CDATA[29]]></wheel_diameter>
		<frame_material><![CDATA[Aluminum]]></frame_material>
		<brake_type><![CDATA[Disk hydraulic]]></brake_type>
	</node>
	<node>
		<sku><![CDATA[249473461]]></sku>
		<category><![CDATA[Bicycles>Mountain Bikes]]></category>
		<tags><![CDATA[For real mans!]]></tags>
		<title><![CDATA[Велосипед Orbea Alma H10-Eagle 29 XL 2021]]></title>
		<price><![CDATA[49756]]></price>
		<color><![CDATA[Metallic Red]]></color>
		<size><![CDATA[XL]]></size>
		<images><![CDATA[https://content1.rozetka.com.ua/goods/images/big/146234705.jpg ]]></images>
		<class><![CDATA[mountin]]></class>
		<number_of_speeds><![CDATA[12]]></number_of_speeds>
		<max_speed><![CDATA[]]></max_speed>
		<wheel_diameter><![CDATA[29]]></wheel_diameter>
		<frame_material><![CDATA[Aluminum]]></frame_material>
		<brake_type><![CDATA[Disk hydraulic]]></brake_type>
	</node>
	<node>
		<sku><![CDATA[249473456]]></sku>
		<category><![CDATA[Bicycles>Mountain Bikes]]></category>
		<tags><![CDATA[For real mans!]]></tags>
		<title><![CDATA[Велосипед Orbea Alma H10-Eagle 29 XL 2021]]></title>
		<price><![CDATA[49756]]></price>
		<color><![CDATA[Bright Red]]></color>
		<size><![CDATA[XL]]></size>
		<images><![CDATA[https://content2.rozetka.com.ua/goods/images/big/146234691.jpg ]]></images>
		<class><![CDATA[mountin]]></class>
		<number_of_speeds><![CDATA[12]]></number_of_speeds>
		<max_speed><![CDATA[]]></max_speed>
		<wheel_diameter><![CDATA[29]]></wheel_diameter>
		<frame_material><![CDATA[Aluminum]]></frame_material>
		<brake_type><![CDATA[Disk hydraulic]]></brake_type>
	</node>
	<node>
		<sku><![CDATA[182598473]]></sku>
		<category><![CDATA[Bicycles>Female]]></category>
		<tags><![CDATA[For ladies]]></tags>
		<title><![CDATA[Велосипед Ardis Berta 26" 17" 2019]]></title>
		<price><![CDATA[4599]]></price>
		<color><![CDATA[White and pink]]></color>
		<size><![CDATA[17]]></size>
		<images><![CDATA[https://content1.rozetka.com.ua/goods/images/big/115926021.jpg ]]></images>
		<class><![CDATA[Female]]></class>
		<number_of_speeds><![CDATA[1]]></number_of_speeds>
		<max_speed><![CDATA[]]></max_speed>
		<wheel_diameter><![CDATA[26]]></wheel_diameter>
		<frame_material><![CDATA[Steel]]></frame_material>
		<brake_type><![CDATA[Coster Brake; V-Brake]]></brake_type>
	</node>
	<node>
		<sku><![CDATA[218609455]]></sku>
		<category><![CDATA[Bicycles>Female]]></category>
		<tags><![CDATA[For ladies]]></tags>
		<title><![CDATA[Велосипед Vento Mistral 27.5" 17"]]></title>
		<price><![CDATA[11999]]></price>
		<color><![CDATA[Light Blue Gloss]]></color>
		<size><![CDATA[17]]></size>
		<images><![CDATA[https://content1.rozetka.com.ua/goods/images/big/131672777.jpg ]]></images>
		<class><![CDATA[Female]]></class>
		<number_of_speeds><![CDATA[21]]></number_of_speeds>
		<max_speed><![CDATA[]]></max_speed>
		<wheel_diameter><![CDATA[27.5]]></wheel_diameter>
		<frame_material><![CDATA[Aluminum]]></frame_material>
		<brake_type><![CDATA[Promax Alloy Mechnical Disc. 160/161]]></brake_type>
	</node>
	<node>
		<sku><![CDATA[218609395]]></sku>
		<category><![CDATA[Bicycles>Female]]></category>
		<tags><![CDATA[For ladies]]></tags>
		<title><![CDATA[Велосипед Vento Mistral 27.5" 17"]]></title>
		<price><![CDATA[11999]]></price>
		<color><![CDATA[White Satin]]></color>
		<size><![CDATA[17]]></size>
		<images><![CDATA[https://content2.rozetka.com.ua/goods/images/big/131672945.jpg ]]></images>
		<class><![CDATA[Female]]></class>
		<number_of_speeds><![CDATA[21]]></number_of_speeds>
		<max_speed><![CDATA[]]></max_speed>
		<wheel_diameter><![CDATA[27.5]]></wheel_diameter>
		<frame_material><![CDATA[Aluminum]]></frame_material>
		<brake_type><![CDATA[Promax Alloy Mechnical Disc. 160/161]]></brake_type>
	</node>
	<node>
		<sku><![CDATA[218609581]]></sku>
		<category><![CDATA[Bicycles>Female]]></category>
		<tags><![CDATA[For ladies]]></tags>
		<title><![CDATA[Велосипед Vento Mistral 27.5" 17"]]></title>
		<price><![CDATA[11999]]></price>
		<color><![CDATA[Coral Gloss]]></color>
		<size><![CDATA[17]]></size>
		<images><![CDATA[https://content.rozetka.com.ua/goods/images/big/131672959.jpg ]]></images>
		<class><![CDATA[Female]]></class>
		<number_of_speeds><![CDATA[21]]></number_of_speeds>
		<max_speed><![CDATA[]]></max_speed>
		<wheel_diameter><![CDATA[27.5]]></wheel_diameter>
		<frame_material><![CDATA[Aluminum]]></frame_material>
		<brake_type><![CDATA[Promax Alloy Mechnical Disc. 160/161]]></brake_type>
	</node>
	<node>
		<sku><![CDATA[218609167]]></sku>
		<category><![CDATA[Bicycles>Female]]></category>
		<tags><![CDATA[For ladies]]></tags>
		<title><![CDATA[Велосипед Vento Levante 27.5" 15.5"]]></title>
		<price><![CDATA[14999]]></price>
		<color><![CDATA[Deep Violet Gloss]]></color>
		<size><![CDATA[15.5]]></size>
		<images><![CDATA[https://content2.rozetka.com.ua/goods/images/big/131672982.jpg ]]></images>
		<class><![CDATA[Female]]></class>
		<number_of_speeds><![CDATA[27]]></number_of_speeds>
		<max_speed><![CDATA[]]></max_speed>
		<wheel_diameter><![CDATA[27.5]]></wheel_diameter>
		<frame_material><![CDATA[Aluminum]]></frame_material>
		<brake_type><![CDATA[Shimano MT200. 160/162]]></brake_type>
	</node>
	<node>
		<sku><![CDATA[218609281]]></sku>
		<category><![CDATA[Bicycles>Female]]></category>
		<tags><![CDATA[For ladies]]></tags>
		<title><![CDATA[Велосипед Vento Levante 27.5" 15.5"]]></title>
		<price><![CDATA[14999]]></price>
		<color><![CDATA[Turqoise Gloss]]></color>
		<size><![CDATA[15.5]]></size>
		<images><![CDATA[https://content2.rozetka.com.ua/goods/images/big/131672746.jpg ]]></images>
		<class><![CDATA[Female]]></class>
		<number_of_speeds><![CDATA[27]]></number_of_speeds>
		<max_speed><![CDATA[]]></max_speed>
		<wheel_diameter><![CDATA[27.5]]></wheel_diameter>
		<frame_material><![CDATA[Aluminum]]></frame_material>
		<brake_type><![CDATA[Shimano MT200. 160/162]]></brake_type>
	</node>
	<node>
		<sku><![CDATA[273266403]]></sku>
		<category><![CDATA[Bicycles>Female]]></category>
		<tags><![CDATA[For ladies]]></tags>
		<title><![CDATA[Велосипед 26" DOROZHNIK RUBY]]></title>
		<price><![CDATA[7000]]></price>
		<color><![CDATA[Black]]></color>
		<size><![CDATA[L]]></size>
		<images><![CDATA[https://content1.rozetka.com.ua/goods/images/big/54862125.png ]]></images>
		<class><![CDATA[Female]]></class>
		<number_of_speeds><![CDATA[7]]></number_of_speeds>
		<max_speed><![CDATA[]]></max_speed>
		<wheel_diameter><![CDATA[26]]></wheel_diameter>
		<frame_material><![CDATA[Aluminum]]></frame_material>
		<brake_type><![CDATA[Lunch brakes]]></brake_type>
	</node>
	<node>
		<sku><![CDATA[293023253]]></sku>
		<category><![CDATA[Bicycles>Female]]></category>
		<tags><![CDATA[For ladies]]></tags>
		<title><![CDATA[Велосипед 27.5" Leon XC-LADY 16.5" 2021]]></title>
		<price><![CDATA[13100]]></price>
		<color><![CDATA[White and pink]]></color>
		<size><![CDATA[17]]></size>
		<images><![CDATA[https://content1.rozetka.com.ua/goods/images/big/173960099.jpg ]]></images>
		<class><![CDATA[Female]]></class>
		<number_of_speeds><![CDATA[24]]></number_of_speeds>
		<max_speed><![CDATA[]]></max_speed>
		<wheel_diameter><![CDATA[27.5]]></wheel_diameter>
		<frame_material><![CDATA[Aluminum]]></frame_material>
		<brake_type><![CDATA[Disk hydraulic]]></brake_type>
	</node>
	<node>
		<sku><![CDATA[268256731]]></sku>
		<category><![CDATA[Bicycles>Female]]></category>
		<tags><![CDATA[For ladies]]></tags>
		<title><![CDATA[Велосипед 26" DOROZHNIK LUX]]></title>
		<price><![CDATA[5800]]></price>
		<color><![CDATA[Plum]]></color>
		<size><![CDATA[17]]></size>
		<images><![CDATA[https://content.rozetka.com.ua/goods/images/big/8189103.jpg ]]></images>
		<class><![CDATA[Female]]></class>
		<number_of_speeds><![CDATA[1]]></number_of_speeds>
		<max_speed><![CDATA[]]></max_speed>
		<wheel_diameter><![CDATA[26]]></wheel_diameter>
		<frame_material><![CDATA[Steel]]></frame_material>
		<brake_type><![CDATA[Lunch brakes]]></brake_type>
	</node>
	<node>
		<sku><![CDATA[268256776]]></sku>
		<category><![CDATA[Bicycles>Female]]></category>
		<tags><![CDATA[For ladies]]></tags>
		<title><![CDATA[Велосипед 26" DOROZHNIK LUX]]></title>
		<price><![CDATA[5800]]></price>
		<color><![CDATA[Anthracite]]></color>
		<size><![CDATA[17]]></size>
		<images><![CDATA[https://content1.rozetka.com.ua/goods/images/big/8189108.jpg ]]></images>
		<class><![CDATA[Female]]></class>
		<number_of_speeds><![CDATA[1]]></number_of_speeds>
		<max_speed><![CDATA[]]></max_speed>
		<wheel_diameter><![CDATA[26]]></wheel_diameter>
		<frame_material><![CDATA[Steel]]></frame_material>
		<brake_type><![CDATA[Lunch brakes]]></brake_type>
	</node>
	<node>
		<sku><![CDATA[268256771]]></sku>
		<category><![CDATA[Bicycles>Female]]></category>
		<tags><![CDATA[For ladies]]></tags>
		<title><![CDATA[Велосипед 26" DOROZHNIK LUX]]></title>
		<price><![CDATA[5800]]></price>
		<color><![CDATA[White]]></color>
		<size><![CDATA[17]]></size>
		<images><![CDATA[https://content.rozetka.com.ua/goods/images/big/8189107.jpg ]]></images>
		<class><![CDATA[Female]]></class>
		<number_of_speeds><![CDATA[1]]></number_of_speeds>
		<max_speed><![CDATA[]]></max_speed>
		<wheel_diameter><![CDATA[26]]></wheel_diameter>
		<frame_material><![CDATA[Steel]]></frame_material>
		<brake_type><![CDATA[Lunch brakes]]></brake_type>
	</node>
	<node>
		<sku><![CDATA[268256786]]></sku>
		<category><![CDATA[Bicycles>Female]]></category>
		<tags><![CDATA[For ladies]]></tags>
		<title><![CDATA[Велосипед 26" DOROZHNIK LUX]]></title>
		<price><![CDATA[5800]]></price>
		<color><![CDATA[Ruby]]></color>
		<size><![CDATA[17]]></size>
		<images><![CDATA[https://content2.rozetka.com.ua/goods/images/big/8189109.jpg ]]></images>
		<class><![CDATA[Female]]></class>
		<number_of_speeds><![CDATA[1]]></number_of_speeds>
		<max_speed><![CDATA[]]></max_speed>
		<wheel_diameter><![CDATA[26]]></wheel_diameter>
		<frame_material><![CDATA[Steel]]></frame_material>
		<brake_type><![CDATA[Lunch brakes]]></brake_type>
	</node>
	<node>
		<sku><![CDATA[12113116]]></sku>
		<category><![CDATA[Electric transport>Unicycles]]></category>
		<tags><![CDATA[For adalts]]></tags>
		<title><![CDATA[Моноколесо Segway Ninebot One S2]]></title>
		<price><![CDATA[16999]]></price>
		<color><![CDATA[White]]></color>
		<size><![CDATA[]]></size>
		<images><![CDATA[https://content2.rozetka.com.ua/goods/images/big/50310041.jpg ]]></images>
		<class><![CDATA[Adalts]]></class>
		<number_of_speeds><![CDATA[]]></number_of_speeds>
		<max_speed><![CDATA[24]]></max_speed>
		<wheel_diameter><![CDATA[14]]></wheel_diameter>
		<frame_material><![CDATA[Steel]]></frame_material>
		<brake_type><![CDATA[Promax Alloy Mechnical Disc. 160/161]]></brake_type>
	</node>
	<node>
		<sku><![CDATA[115350385]]></sku>
		<category><![CDATA[Electric transport>Unicycles]]></category>
		<tags><![CDATA[For adalts]]></tags>
		<title><![CDATA[Моноколесо Segway Ninebot Z10]]></title>
		<price><![CDATA[64999]]></price>
		<color><![CDATA[Black]]></color>
		<size><![CDATA[]]></size>
		<images><![CDATA[https://content2.rozetka.com.ua/goods/images/big/90168290.jpg ]]></images>
		<class><![CDATA[Adalts]]></class>
		<number_of_speeds><![CDATA[]]></number_of_speeds>
		<max_speed><![CDATA[45]]></max_speed>
		<wheel_diameter><![CDATA[18]]></wheel_diameter>
		<frame_material><![CDATA[Steel]]></frame_material>
		<brake_type><![CDATA[Promax Alloy Mechnical Disc. 160/161]]></brake_type>
	</node>
	<node>
		<sku><![CDATA[49825182]]></sku>
		<category><![CDATA[Electric transport>Unicycles]]></category>
		<tags><![CDATA[For adalts]]></tags>
		<title><![CDATA[Моноколесо KingSong 14M 174Wh/800W]]></title>
		<price><![CDATA[13330]]></price>
		<color><![CDATA[White]]></color>
		<size><![CDATA[]]></size>
		<images><![CDATA[https://content.rozetka.com.ua/goods/images/big/12357817.jpg|https://content.rozetka.com.ua/goods/images/big/12357828.jpg|https://content.rozetka.com.ua/goods/images/big/12357833.jpg|https://content1.rozetka.com.ua/goods/images/big/12357841.jpg|https://content1.rozetka.com.ua/goods/images/big/12357845.jpg|https://content.rozetka.com.ua/goods/images/big/12357879.jpg|https://content1.rozetka.com.ua/goods/images/big/12357898.jpg|https://content2.rozetka.com.ua/goods/images/big/12357913.jpg]]></images>
		<class><![CDATA[Adalts]]></class>
		<number_of_speeds><![CDATA[]]></number_of_speeds>
		<max_speed><![CDATA[20]]></max_speed>
		<wheel_diameter><![CDATA[14]]></wheel_diameter>
		<frame_material><![CDATA[Steel]]></frame_material>
		<brake_type><![CDATA[Promax Alloy Mechnical Disc. 160/161]]></brake_type>
	</node>
	<node>
		<sku><![CDATA[195037858]]></sku>
		<category><![CDATA[Electric transport>Unicycles]]></category>
		<tags><![CDATA[For kids]]></tags>
		<title><![CDATA[МоноКолесо Z1]]></title>
		<price><![CDATA[5999]]></price>
		<color><![CDATA[Blue]]></color>
		<size><![CDATA[]]></size>
		<images><![CDATA[https://content1.rozetka.com.ua/goods/images/big/120700005.jpg|https://content2.rozetka.com.ua/goods/images/big/120700013.jpg]]></images>
		<class><![CDATA[Kids]]></class>
		<number_of_speeds><![CDATA[]]></number_of_speeds>
		<max_speed><![CDATA[18]]></max_speed>
		<wheel_diameter><![CDATA[14]]></wheel_diameter>
		<frame_material><![CDATA[Steel]]></frame_material>
		<brake_type><![CDATA[Disk hydraulic]]></brake_type>
	</node>
	<node>
		<sku><![CDATA[195037851]]></sku>
		<category><![CDATA[Electric transport>Unicycles]]></category>
		<tags><![CDATA[For kids]]></tags>
		<title><![CDATA[МоноКолесо X5 Карбон 2-х колесное ]]></title>
		<price><![CDATA[7999]]></price>
		<color><![CDATA[Black]]></color>
		<size><![CDATA[]]></size>
		<images><![CDATA[https://content.rozetka.com.ua/goods/images/big/120700006.jpg|https://content1.rozetka.com.ua/goods/images/big/120700010.jpg|https://content.rozetka.com.ua/goods/images/big/120700027.jpg]]></images>
		<class><![CDATA[Kids]]></class>
		<number_of_speeds><![CDATA[]]></number_of_speeds>
		<max_speed><![CDATA[18]]></max_speed>
		<wheel_diameter><![CDATA[14]]></wheel_diameter>
		<frame_material><![CDATA[Carbon]]></frame_material>
		<brake_type><![CDATA[Disk hydraulic]]></brake_type>
	</node>
	<node>
		<sku><![CDATA[49825246]]></sku>
		<category><![CDATA[Electric transport>Unicycles]]></category>
		<tags><![CDATA[For kids]]></tags>
		<title><![CDATA[Моноколесо KingSong 14M 174Wh/800W]]></title>
		<price><![CDATA[13330]]></price>
		<color><![CDATA[Black]]></color>
		<size><![CDATA[]]></size>
		<images><![CDATA[https://content1.rozetka.com.ua/goods/images/big/12358001.png|https://content.rozetka.com.ua/goods/images/big/12358010.png|https://content1.rozetka.com.ua/goods/images/big/12358031.png|https://content1.rozetka.com.ua/goods/images/big/12358048.png|https://content1.rozetka.com.ua/goods/images/big/12358058.png]]></images>
		<class><![CDATA[Kids]]></class>
		<number_of_speeds><![CDATA[]]></number_of_speeds>
		<max_speed><![CDATA[20]]></max_speed>
		<wheel_diameter><![CDATA[14]]></wheel_diameter>
		<frame_material><![CDATA[Steel]]></frame_material>
		<brake_type><![CDATA[Promax Alloy Mechnical Disc. 160/161]]></brake_type>
	</node>
	<node>
		<sku><![CDATA[49825206]]></sku>
		<category><![CDATA[Electric transport>Unicycles]]></category>
		<tags><![CDATA[For adalts]]></tags>
		<title><![CDATA[Моноколесо KingSong 14D 420Wh/800W]]></title>
		<price><![CDATA[21990]]></price>
		<color><![CDATA[Black]]></color>
		<size><![CDATA[]]></size>
		<images><![CDATA[https://content1.rozetka.com.ua/goods/images/big/12358001.png|https://content.rozetka.com.ua/goods/images/big/12358010.png|https://content1.rozetka.com.ua/goods/images/big/12358031.png|https://content1.rozetka.com.ua/goods/images/big/12358048.png|https://content1.rozetka.com.ua/goods/images/big/12358058.png]]></images>
		<class><![CDATA[Adalts]]></class>
		<number_of_speeds><![CDATA[]]></number_of_speeds>
		<max_speed><![CDATA[30]]></max_speed>
		<wheel_diameter><![CDATA[14]]></wheel_diameter>
		<frame_material><![CDATA[Steel]]></frame_material>
		<brake_type><![CDATA[Promax Alloy Mechnical Disc. 160/161]]></brake_type>
	</node>
	<node>
		<sku><![CDATA[136070346]]></sku>
		<category><![CDATA[Electric transport>Unicycles]]></category>
		<tags><![CDATA[For adalts]]></tags>
		<title><![CDATA[Моноколесо KingSong 18L 1036Wh/2000W]]></title>
		<price><![CDATA[43990]]></price>
		<color><![CDATA[Black]]></color>
		<size><![CDATA[]]></size>
		<images><![CDATA[https://content.rozetka.com.ua/goods/images/big/18158535.jpg|https://content1.rozetka.com.ua/goods/images/big/18158567.jpg|https://content2.rozetka.com.ua/goods/images/big/18158667.jpg|https://content1.rozetka.com.ua/goods/images/big/18158692.jpg|https://content2.rozetka.com.ua/goods/images/big/18158708.jpg]]></images>
		<class><![CDATA[Adalts]]></class>
		<number_of_speeds><![CDATA[]]></number_of_speeds>
		<max_speed><![CDATA[50]]></max_speed>
		<wheel_diameter><![CDATA[18]]></wheel_diameter>
		<frame_material><![CDATA[Steel]]></frame_material>
		<brake_type><![CDATA[Promax Alloy Mechnical Disc. 160/161]]></brake_type>
	</node>
	<node>
		<sku><![CDATA[237025285]]></sku>
		<category><![CDATA[Electric transport>Unicycles]]></category>
		<tags><![CDATA[For adalts]]></tags>
		<title><![CDATA[Моноколесо InMotion V11]]></title>
		<price><![CDATA[58999]]></price>
		<color><![CDATA[Black]]></color>
		<size><![CDATA[]]></size>
		<images><![CDATA[https://content1.rozetka.com.ua/goods/images/big/140588296.jpg|https://content.rozetka.com.ua/goods/images/big/140588309.jpg|https://content.rozetka.com.ua/goods/images/big/140588342.jpg|https://content1.rozetka.com.ua/goods/images/big/140588353.jpg|https://content.rozetka.com.ua/goods/images/big/140588361.jpg]]></images>
		<class><![CDATA[Adalts]]></class>
		<number_of_speeds><![CDATA[]]></number_of_speeds>
		<max_speed><![CDATA[55]]></max_speed>
		<wheel_diameter><![CDATA[18]]></wheel_diameter>
		<frame_material><![CDATA[Steel]]></frame_material>
		<brake_type><![CDATA[Promax Alloy Mechnical Disc. 160/161]]></brake_type>
	</node>
	<node>
		<sku><![CDATA[110982376]]></sku>
		<category><![CDATA[Electric transport>Unicycles]]></category>
		<tags><![CDATA[For kids]]></tags>
		<title><![CDATA[Моноколесо зі світловими ефектами HL-888]]></title>
		<price><![CDATA[6989]]></price>
		<color><![CDATA[Blue]]></color>
		<size><![CDATA[]]></size>
		<images><![CDATA[https://content2.rozetka.com.ua/goods/images/big/88389676.png|https://content.rozetka.com.ua/goods/images/big/88389702.jpg]]></images>
		<class><![CDATA[Kids]]></class>
		<number_of_speeds><![CDATA[]]></number_of_speeds>
		<max_speed><![CDATA[35]]></max_speed>
		<wheel_diameter><![CDATA[14]]></wheel_diameter>
		<frame_material><![CDATA[Aluminum]]></frame_material>
		<brake_type><![CDATA[Disk hydraulic]]></brake_type>
	</node>
	<node>
		<sku><![CDATA[200605639]]></sku>
		<category><![CDATA[Electric transport>Electric bicycles]]></category>
		<tags><![CDATA[Ecological]]></tags>
		<title><![CDATA[Електровелосипед Maxxter City]]></title>
		<price><![CDATA[18499]]></price>
		<color><![CDATA[Whire]]></color>
		<size><![CDATA[18]]></size>
		<images><![CDATA[https://content1.rozetka.com.ua/goods/images/big/123537798.jpg|https://content1.rozetka.com.ua/goods/images/big/123537806.jpg|https://content.rozetka.com.ua/goods/images/big/123537748.jpg|https://content1.rozetka.com.ua/goods/images/big/123537815.jpg|https://content.rozetka.com.ua/goods/images/big/123537828.jpg]]></images>
		<class><![CDATA[City]]></class>
		<number_of_speeds><![CDATA[]]></number_of_speeds>
		<max_speed><![CDATA[25]]></max_speed>
		<wheel_diameter><![CDATA[20]]></wheel_diameter>
		<frame_material><![CDATA[Aluminum]]></frame_material>
		<brake_type><![CDATA[Promax Alloy Mechnical Disc. 160/161]]></brake_type>
	</node>
	<node>
		<sku><![CDATA[200604769]]></sku>
		<category><![CDATA[Electric transport>Electric bicycles]]></category>
		<tags><![CDATA[Ecological]]></tags>
		<title><![CDATA[Електровелосипед Maxxter City]]></title>
		<price><![CDATA[18499]]></price>
		<color><![CDATA[Gray]]></color>
		<size><![CDATA[18]]></size>
		<images><![CDATA[https://content1.rozetka.com.ua/goods/images/big/123537509.jpg|https://content.rozetka.com.ua/goods/images/big/123537524.jpg|https://content.rozetka.com.ua/goods/images/big/123537533.jpg|https://content1.rozetka.com.ua/goods/images/big/123537547.jpg]]></images>
		<class><![CDATA[City]]></class>
		<number_of_speeds><![CDATA[]]></number_of_speeds>
		<max_speed><![CDATA[25]]></max_speed>
		<wheel_diameter><![CDATA[20]]></wheel_diameter>
		<frame_material><![CDATA[Aluminum]]></frame_material>
		<brake_type><![CDATA[Promax Alloy Mechnical Disc. 160/161]]></brake_type>
	</node>
	<node>
		<sku><![CDATA[78339986]]></sku>
		<category><![CDATA[Electric transport>Electric bicycles]]></category>
		<tags><![CDATA[Ecological]]></tags>
		<title><![CDATA[Електровелосипед TRINX E-Bike X1E 17 Matt-Black-Green-Blue (X1EMBGB)]]></title>
		<price><![CDATA[27898]]></price>
		<color><![CDATA[Matt-Black-Green-Blue]]></color>
		<size><![CDATA[18]]></size>
		<images><![CDATA[https://content.rozetka.com.ua/goods/images/big/13976900.jpg|https://content.rozetka.com.ua/goods/images/big/13976978.jpg|https://content2.rozetka.com.ua/goods/images/big/13976920.jpg|https://content1.rozetka.com.ua/goods/images/big/13976922.jpg|https://content1.rozetka.com.ua/goods/images/big/13976931.jpg]]></images>
		<class><![CDATA[mountin]]></class>
		<number_of_speeds><![CDATA[]]></number_of_speeds>
		<max_speed><![CDATA[30]]></max_speed>
		<wheel_diameter><![CDATA[26]]></wheel_diameter>
		<frame_material><![CDATA[Steel]]></frame_material>
		<brake_type><![CDATA[Disk hydraulic]]></brake_type>
	</node>
	<node>
		<sku><![CDATA[200606329]]></sku>
		<category><![CDATA[Electric transport>Electric bicycles]]></category>
		<tags><![CDATA[Ecological]]></tags>
		<title><![CDATA[Електровелосипед Maxxter Ruffer Black-Green]]></title>
		<price><![CDATA[21998]]></price>
		<color><![CDATA[Black-Green]]></color>
		<size><![CDATA[16]]></size>
		<images><![CDATA[https://content1.rozetka.com.ua/goods/images/big/123538709.jpg|https://content.rozetka.com.ua/goods/images/big/123538780.jpg|https://content2.rozetka.com.ua/goods/images/big/123538782.jpg|https://content2.rozetka.com.ua/goods/images/big/123538784.jpg|https://content2.rozetka.com.ua/goods/images/big/123538787.jpg|https://content1.rozetka.com.ua/goods/images/big/123538789.jpg]]></images>
		<class><![CDATA[City]]></class>
		<number_of_speeds><![CDATA[]]></number_of_speeds>
		<max_speed><![CDATA[25]]></max_speed>
		<wheel_diameter><![CDATA[20]]></wheel_diameter>
		<frame_material><![CDATA[Aluminum]]></frame_material>
		<brake_type><![CDATA[Disk hydraulic]]></brake_type>
	</node>
	<node>
		<sku><![CDATA[200672083]]></sku>
		<category><![CDATA[Electric transport>Electric bicycles]]></category>
		<tags><![CDATA[Ecological]]></tags>
		<title><![CDATA[Електровелосипед Maxxter Mini Black-White]]></title>
		<price><![CDATA[17999]]></price>
		<color><![CDATA[ Black-White]]></color>
		<size><![CDATA[14]]></size>
		<images><![CDATA[https://content2.rozetka.com.ua/goods/images/big/123561516.jpg|https://content2.rozetka.com.ua/goods/images/big/123561518.jpg|https://content1.rozetka.com.ua/goods/images/big/123561521.jpg|https://content.rozetka.com.ua/goods/images/big/123561525.jpg|https://content.rozetka.com.ua/goods/images/big/123561527.jpg|https://content2.rozetka.com.ua/goods/images/big/123561529.jpg]]></images>
		<class><![CDATA[City]]></class>
		<number_of_speeds><![CDATA[]]></number_of_speeds>
		<max_speed><![CDATA[25]]></max_speed>
		<wheel_diameter><![CDATA[14]]></wheel_diameter>
		<frame_material><![CDATA[Aluminum]]></frame_material>
		<brake_type><![CDATA[Disk hydraulic]]></brake_type>
	</node>
	<node>
		<sku><![CDATA[200675389]]></sku>
		<category><![CDATA[Electric transport>Electric bicycles]]></category>
		<tags><![CDATA[Ecological]]></tags>
		<title><![CDATA[Електровелосипед Maxxter Urban Plus Yellow-Black]]></title>
		<price><![CDATA[18998]]></price>
		<color><![CDATA[Yellow-Black]]></color>
		<size><![CDATA[14]]></size>
		<images><![CDATA[https://content.rozetka.com.ua/goods/images/big/123562829.jpg|https://content1.rozetka.com.ua/goods/images/big/123562843.jpg|https://content2.rozetka.com.ua/goods/images/big/123562852.jpg|https://content.rozetka.com.ua/goods/images/big/123562865.jpg|https://content2.rozetka.com.ua/goods/images/big/123562883.jpg|https://content2.rozetka.com.ua/goods/images/big/123562898.jpg]]></images>
		<class><![CDATA[City]]></class>
		<number_of_speeds><![CDATA[]]></number_of_speeds>
		<max_speed><![CDATA[25]]></max_speed>
		<wheel_diameter><![CDATA[14]]></wheel_diameter>
		<frame_material><![CDATA[Aluminum]]></frame_material>
		<brake_type><![CDATA[Disk hydraulic]]></brake_type>
	</node>
	<node>
		<sku><![CDATA[95831932]]></sku>
		<category><![CDATA[Electric transport>Electric bicycles]]></category>
		<tags><![CDATA[Ecological]]></tags>
		<title><![CDATA[Електровелосипед TRINX E-Bike Sella 2.0 17]]></title>
		<price><![CDATA[29000]]></price>
		<color><![CDATA[Black]]></color>
		<size><![CDATA[18]]></size>
		<images><![CDATA[https://content.rozetka.com.ua/goods/images/big/15071285.jpg|https://content1.rozetka.com.ua/goods/images/big/15071242.jpg|https://content1.rozetka.com.ua/goods/images/big/15071271.jpg|https://content2.rozetka.com.ua/goods/images/big/15071316.jpg|https://content2.rozetka.com.ua/goods/images/big/15071422.jpg]]></images>
		<class><![CDATA[City]]></class>
		<number_of_speeds><![CDATA[]]></number_of_speeds>
		<max_speed><![CDATA[30]]></max_speed>
		<wheel_diameter><![CDATA[24]]></wheel_diameter>
		<frame_material><![CDATA[Aluminum]]></frame_material>
		<brake_type><![CDATA[Disk hydraulic]]></brake_type>
	</node>
	<node>
		<sku><![CDATA[95829988]]></sku>
		<category><![CDATA[Electric transport>Electric bicycles]]></category>
		<tags><![CDATA[Ecological]]></tags>
		<title><![CDATA[Електровелосипед TRINX E-Bike Sella 2.0 17]]></title>
		<price><![CDATA[29000]]></price>
		<color><![CDATA[Champagne-Gold]]></color>
		<size><![CDATA[18]]></size>
		<images><![CDATA[https://content.rozetka.com.ua/goods/images/big/15071111.jpg|https://content2.rozetka.com.ua/goods/images/big/15070973.jpg|https://content1.rozetka.com.ua/goods/images/big/15070980.jpg|https://content.rozetka.com.ua/goods/images/big/15071088.jpg|https://content1.rozetka.com.ua/goods/images/big/15071153.jpg]]></images>
		<class><![CDATA[City]]></class>
		<number_of_speeds><![CDATA[]]></number_of_speeds>
		<max_speed><![CDATA[30]]></max_speed>
		<wheel_diameter><![CDATA[24]]></wheel_diameter>
		<frame_material><![CDATA[Aluminum]]></frame_material>
		<brake_type><![CDATA[Disk hydraulic]]></brake_type>
	</node>
	<node>
		<sku><![CDATA[190032452]]></sku>
		<category><![CDATA[Electric transport>Electric bicycles]]></category>
		<tags><![CDATA[Ecological]]></tags>
		<title><![CDATA[Електровелосипед Zhengbu H1Black from red]]></title>
		<price><![CDATA[22599]]></price>
		<color><![CDATA[Black from red]]></color>
		<size><![CDATA[17]]></size>
		<images><![CDATA[https://content.rozetka.com.ua/goods/images/big/118973308.jpg|https://content1.rozetka.com.ua/goods/images/big/118973313.jpg|https://content.rozetka.com.ua/goods/images/big/118973344.jpg|https://content2.rozetka.com.ua/goods/images/big/118973377.jpg|https://content.rozetka.com.ua/goods/images/big/118973394.jpg|https://content.rozetka.com.ua/goods/images/big/118973407.jpg]]></images>
		<class><![CDATA[mountin]]></class>
		<number_of_speeds><![CDATA[]]></number_of_speeds>
		<max_speed><![CDATA[50]]></max_speed>
		<wheel_diameter><![CDATA[26]]></wheel_diameter>
		<frame_material><![CDATA[Aluminum]]></frame_material>
		<brake_type><![CDATA[Disk hydraulic]]></brake_type>
	</node>
	<node>
		<sku><![CDATA[151094672]]></sku>
		<category><![CDATA[Electric transport>Electric bicycles]]></category>
		<tags><![CDATA[Ecological]]></tags>
		<title><![CDATA[Електровелосипед (трицикл) Skybike 3-Cycle синій]]></title>
		<price><![CDATA[21097]]></price>
		<color><![CDATA[Blue]]></color>
		<size><![CDATA[16]]></size>
		<images><![CDATA[https://content.rozetka.com.ua/goods/images/big/19091586.jpg|https://content1.rozetka.com.ua/goods/images/big/19091641.jpg|https://content2.rozetka.com.ua/goods/images/big/19091655.jpg|https://content1.rozetka.com.ua/goods/images/big/19091689.jpg]]></images>
		<class><![CDATA[City]]></class>
		<number_of_speeds><![CDATA[]]></number_of_speeds>
		<max_speed><![CDATA[25]]></max_speed>
		<wheel_diameter><![CDATA[24]]></wheel_diameter>
		<frame_material><![CDATA[Steel]]></frame_material>
		<brake_type><![CDATA[Disk drumed]]></brake_type>
	</node>
	<node>
		<sku><![CDATA[151094532]]></sku>
		<category><![CDATA[Electric transport>Electric bicycles]]></category>
		<tags><![CDATA[Ecological]]></tags>
		<title><![CDATA[Електровелосипед (трицикл) Skybike 3-Cycle червоний]]></title>
		<price><![CDATA[21097]]></price>
		<color><![CDATA[Red]]></color>
		<size><![CDATA[16]]></size>
		<images><![CDATA[https://content1.rozetka.com.ua/goods/images/big/19091675.jpg|https://content2.rozetka.com.ua/goods/images/big/19091687.jpg|https://content.rozetka.com.ua/goods/images/big/19091696.jpg|https://content1.rozetka.com.ua/goods/images/big/19091700.jpg]]></images>
		<class><![CDATA[City]]></class>
		<number_of_speeds><![CDATA[]]></number_of_speeds>
		<max_speed><![CDATA[25]]></max_speed>
		<wheel_diameter><![CDATA[24]]></wheel_diameter>
		<frame_material><![CDATA[Steel]]></frame_material>
		<brake_type><![CDATA[Disk drumed]]></brake_type>
	</node>
	<node>
		<sku><![CDATA[290250803]]></sku>
		<category><![CDATA[Electric transport>Electric bicycles]]></category>
		<tags><![CDATA[Ecological]]></tags>
		<title><![CDATA[Електровелосипед складаний Formula Smart складаний передній привід із заниженою рамою 36V 10 Ah 350]]></title>
		<price><![CDATA[15290]]></price>
		<color><![CDATA[Black]]></color>
		<size><![CDATA[16]]></size>
		<images><![CDATA[https://content2.rozetka.com.ua/goods/images/big/171130457.jpg|https://content1.rozetka.com.ua/goods/images/big/171130458.jpg|https://content1.rozetka.com.ua/goods/images/big/171130459.jpg|https://content2.rozetka.com.ua/goods/images/big/171130462.jpg]]></images>
		<class><![CDATA[City]]></class>
		<number_of_speeds><![CDATA[]]></number_of_speeds>
		<max_speed><![CDATA[30]]></max_speed>
		<wheel_diameter><![CDATA[24]]></wheel_diameter>
		<frame_material><![CDATA[Steel]]></frame_material>
		<brake_type><![CDATA[Disk hydraulic]]></brake_type>
	</node>
	<node>
		<sku><![CDATA[290293683]]></sku>
		<category><![CDATA[Electric transport>Electric bicycles]]></category>
		<tags><![CDATA[Ecological]]></tags>
		<title><![CDATA[Електровелосипед складаний Formula Smart складаний передній привід із заниженою рамою 36V 10 Ah 350]]></title>
		<price><![CDATA[15290]]></price>
		<color><![CDATA[Green]]></color>
		<size><![CDATA[16]]></size>
		<images><![CDATA[https://content1.rozetka.com.ua/goods/images/big/171230195.jpg|https://content.rozetka.com.ua/goods/images/big/171230197.jpg|https://content1.rozetka.com.ua/goods/images/big/171230199.jpg|https://content1.rozetka.com.ua/goods/images/big/171230200.jpg]]></images>
		<class><![CDATA[City]]></class>
		<number_of_speeds><![CDATA[]]></number_of_speeds>
		<max_speed><![CDATA[30]]></max_speed>
		<wheel_diameter><![CDATA[24]]></wheel_diameter>
		<frame_material><![CDATA[Steel]]></frame_material>
		<brake_type><![CDATA[Disk hydraulic]]></brake_type>
	</node>
	<node>
		<sku><![CDATA[290435808]]></sku>
		<category><![CDATA[Electric transport>Electric bicycles]]></category>
		<tags><![CDATA[Ecological]]></tags>
		<title><![CDATA[Електровелосипед складаний Formula Smart складаний передній привід із заниженою рамою 36V 10 Ah 350]]></title>
		<price><![CDATA[15290]]></price>
		<color><![CDATA[Red]]></color>
		<size><![CDATA[16]]></size>
		<images><![CDATA[https://content1.rozetka.com.ua/goods/images/big/171230172.jpg|https://content1.rozetka.com.ua/goods/images/big/171230176.jpg|https://content1.rozetka.com.ua/goods/images/big/171230180.jpg|https://content.rozetka.com.ua/goods/images/big/171230183.jpg]]></images>
		<class><![CDATA[City]]></class>
		<number_of_speeds><![CDATA[]]></number_of_speeds>
		<max_speed><![CDATA[30]]></max_speed>
		<wheel_diameter><![CDATA[24]]></wheel_diameter>
		<frame_material><![CDATA[Steel]]></frame_material>
		<brake_type><![CDATA[Disk hydraulic]]></brake_type>
	</node>
	<node>
		<sku><![CDATA[290435808]]></sku>
		<category><![CDATA[Electric transport>Electric bicycles]]></category>
		<tags><![CDATA[Ecological]]></tags>
		<title><![CDATA[Електровелосипед складаний Formula Smart передній привід занижена рама 36V 10 Ah 350 Вт чорно-сірий]]></title>
		<price><![CDATA[15290]]></price>
		<color><![CDATA[Black]]></color>
		<size><![CDATA[16]]></size>
		<images><![CDATA[https://content1.rozetka.com.ua/goods/images/big/171129271.jpg|https://content1.rozetka.com.ua/goods/images/big/171129272.jpg|https://content1.rozetka.com.ua/goods/images/big/171129275.jpg|https://content.rozetka.com.ua/goods/images/big/171129276.jpg]]></images>
		<class><![CDATA[City]]></class>
		<number_of_speeds><![CDATA[]]></number_of_speeds>
		<max_speed><![CDATA[30]]></max_speed>
		<wheel_diameter><![CDATA[24]]></wheel_diameter>
		<frame_material><![CDATA[Steel]]></frame_material>
		<brake_type><![CDATA[Disk hydraulic]]></brake_type>
	</node>
	<node>
		<sku><![CDATA[295005013]]></sku>
		<category><![CDATA[Electric transport>Electric bicycles]]></category>
		<tags><![CDATA[Ecological]]></tags>
		<title><![CDATA[Електровелосипед Kerambit 26" рама 17" 36V 12Ah 500W складаний з багажником чорно-жовтий]]></title>
		<price><![CDATA[20570]]></price>
		<color><![CDATA[Black-Yellow]]></color>
		<size><![CDATA[18]]></size>
		<images><![CDATA[https://content1.rozetka.com.ua/goods/images/big/175754684.jpg|https://content2.rozetka.com.ua/goods/images/big/175754685.jpg|https://content2.rozetka.com.ua/goods/images/big/175754686.jpg|https://content.rozetka.com.ua/goods/images/big/175754687.jpg]]></images>
		<class><![CDATA[mountin]]></class>
		<number_of_speeds><![CDATA[]]></number_of_speeds>
		<max_speed><![CDATA[40]]></max_speed>
		<wheel_diameter><![CDATA[26]]></wheel_diameter>
		<frame_material><![CDATA[Steel]]></frame_material>
		<brake_type><![CDATA[Disk hydraulic]]></brake_type>
	</node>
	<node>
		<sku><![CDATA[274231613]]></sku>
		<category><![CDATA[Electric transport>Electric bicycles]]></category>
		<tags><![CDATA[Ecological]]></tags>
		<title><![CDATA[Электровелосипед LIDO 350Вт 12Ач с LCD пультом управления серый с белым]]></title>
		<price><![CDATA[16950]]></price>
		<color><![CDATA[Gray-White]]></color>
		<size><![CDATA[18]]></size>
		<images><![CDATA[https://content1.rozetka.com.ua/goods/images/big/73998241.jpg]]></images>
		<class><![CDATA[City]]></class>
		<number_of_speeds><![CDATA[]]></number_of_speeds>
		<max_speed><![CDATA[40]]></max_speed>
		<wheel_diameter><![CDATA[26]]></wheel_diameter>
		<frame_material><![CDATA[Steel]]></frame_material>
		<brake_type><![CDATA[Disk hydraulic]]></brake_type>
	</node>
	<node>
		<sku><![CDATA[265220041]]></sku>
		<category><![CDATA[Electric transport>Electric bicycles]]></category>
		<tags><![CDATA[Ecological]]></tags>
		<title><![CDATA[Електровелосипед складаний FOLD 350Вт 10 ач з LCD пультом управління червоний]]></title>
		<price><![CDATA[16990]]></price>
		<color><![CDATA[Red]]></color>
		<size><![CDATA[16]]></size>
		<images><![CDATA[https://content2.rozetka.com.ua/goods/images/big/5307525.jpg]]></images>
		<class><![CDATA[City]]></class>
		<number_of_speeds><![CDATA[]]></number_of_speeds>
		<max_speed><![CDATA[40]]></max_speed>
		<wheel_diameter><![CDATA[26]]></wheel_diameter>
		<frame_material><![CDATA[Steel]]></frame_material>
		<brake_type><![CDATA[Disk hydraulic]]></brake_type>
	</node>
	<node>
		<sku><![CDATA[81828309]]></sku>
		<category><![CDATA[Electric transport>Electric bicycles]]></category>
		<tags><![CDATA[Ecological]]></tags>
		<title><![CDATA[Електровелосипед E-motion Fatbike GT 48V 15Ah 1000W 26" / рама 19"]]></title>
		<price><![CDATA[33990]]></price>
		<color><![CDATA[Yellow]]></color>
		<size><![CDATA[19]]></size>
		<images><![CDATA[https://content.rozetka.com.ua/goods/images/big/14215641.jpg|https://content.rozetka.com.ua/goods/images/big/14215650.jpg|https://content.rozetka.com.ua/goods/images/big/14215656.jpg]]></images>
		<class><![CDATA[mountin]]></class>
		<number_of_speeds><![CDATA[]]></number_of_speeds>
		<max_speed><![CDATA[50]]></max_speed>
		<wheel_diameter><![CDATA[26]]></wheel_diameter>
		<frame_material><![CDATA[Steel]]></frame_material>
		<brake_type><![CDATA[Disk hydraulic]]></brake_type>
	</node>
	<node>
		<sku><![CDATA[157275581]]></sku>
		<category><![CDATA[Electric transport>Electric bicycles]]></category>
		<tags><![CDATA[Ecological]]></tags>
		<title><![CDATA[Електровелосипед E-motion Fatbike GT 48V 15Ah 1000W 26" / рама 19"]]></title>
		<price><![CDATA[33990]]></price>
		<color><![CDATA[Blue]]></color>
		<size><![CDATA[19]]></size>
		<images><![CDATA[https://content.rozetka.com.ua/goods/images/big/19650594.jpg|https://content1.rozetka.com.ua/goods/images/big/19650607.jpg|https://content2.rozetka.com.ua/goods/images/big/19650626.jpg]]></images>
		<class><![CDATA[mountin]]></class>
		<number_of_speeds><![CDATA[]]></number_of_speeds>
		<max_speed><![CDATA[50]]></max_speed>
		<wheel_diameter><![CDATA[26]]></wheel_diameter>
		<frame_material><![CDATA[Steel]]></frame_material>
		<brake_type><![CDATA[Disk hydraulic]]></brake_type>
	</node>
	<node>
		<sku><![CDATA[157275560]]></sku>
		<category><![CDATA[Electric transport>Electric bicycles]]></category>
		<tags><![CDATA[Ecological]]></tags>
		<title><![CDATA[Електровелосипед E-motion Fatbike GT 48V 15Ah 1000W 26" / рама 19"]]></title>
		<price><![CDATA[33990]]></price>
		<color><![CDATA[Black]]></color>
		<size><![CDATA[19]]></size>
		<images><![CDATA[https://content1.rozetka.com.ua/goods/images/big/19650732.jpg|https://content2.rozetka.com.ua/goods/images/big/19650739.jpg|https://content1.rozetka.com.ua/goods/images/big/19650744.jpg]]></images>
		<class><![CDATA[mountin]]></class>
		<number_of_speeds><![CDATA[]]></number_of_speeds>
		<max_speed><![CDATA[50]]></max_speed>
		<wheel_diameter><![CDATA[26]]></wheel_diameter>
		<frame_material><![CDATA[Steel]]></frame_material>
		<brake_type><![CDATA[Disk hydraulic]]></brake_type>
	</node>
	<node>
		<sku><![CDATA[157275511]]></sku>
		<category><![CDATA[Electric transport>Electric bicycles]]></category>
		<tags><![CDATA[Ecological]]></tags>
		<title><![CDATA[Електровелосипед E-motion Fatbike GT 48V 15Ah 1000W 26" / рама 19"]]></title>
		<price><![CDATA[33990]]></price>
		<color><![CDATA[Green]]></color>
		<size><![CDATA[19]]></size>
		<images><![CDATA[https://content1.rozetka.com.ua/goods/images/big/19650614.jpg|https://content2.rozetka.com.ua/goods/images/big/19650634.jpg|https://content2.rozetka.com.ua/goods/images/big/19650643.jpg]]></images>
		<class><![CDATA[mountin]]></class>
		<number_of_speeds><![CDATA[]]></number_of_speeds>
		<max_speed><![CDATA[50]]></max_speed>
		<wheel_diameter><![CDATA[26]]></wheel_diameter>
		<frame_material><![CDATA[Steel]]></frame_material>
		<brake_type><![CDATA[Disk hydraulic]]></brake_type>
	</node>
	<node>
		<sku><![CDATA[157275763]]></sku>
		<category><![CDATA[Electric transport>Electric bicycles]]></category>
		<tags><![CDATA[Ecological]]></tags>
		<title><![CDATA[Електровелосипед E-motion Fatbike GT 48V 15Ah 1000W 26" / рама 19"]]></title>
		<price><![CDATA[33990]]></price>
		<color><![CDATA[Red]]></color>
		<size><![CDATA[19]]></size>
		<images><![CDATA[https://content.rozetka.com.ua/goods/images/big/19650642.jpg|https://content.rozetka.com.ua/goods/images/big/19650653.jpg|https://content1.rozetka.com.ua/goods/images/big/19650675.jpg]]></images>
		<class><![CDATA[mountin]]></class>
		<number_of_speeds><![CDATA[]]></number_of_speeds>
		<max_speed><![CDATA[50]]></max_speed>
		<wheel_diameter><![CDATA[26]]></wheel_diameter>
		<frame_material><![CDATA[Steel]]></frame_material>
		<brake_type><![CDATA[Disk hydraulic]]></brake_type>
	</node>
	<node>
		<sku><![CDATA[220988719]]></sku>
		<category><![CDATA[Electric transport>Electric bicycles]]></category>
		<tags><![CDATA[Ecological]]></tags>
		<title><![CDATA[Електровелосипед Mustang Woman 26 колесо 36В 350Вт 8Ач літій іонний акумулятор, чорний]]></title>
		<price><![CDATA[16880]]></price>
		<color><![CDATA[Black]]></color>
		<size><![CDATA[18]]></size>
		<images><![CDATA[https://content.rozetka.com.ua/goods/images/big/25556843.jpg|https://content2.rozetka.com.ua/goods/images/big/25556898.jpg|https://content2.rozetka.com.ua/goods/images/big/25556898.jpg]]></images>
		<class><![CDATA[City]]></class>
		<number_of_speeds><![CDATA[]]></number_of_speeds>
		<max_speed><![CDATA[40]]></max_speed>
		<wheel_diameter><![CDATA[26]]></wheel_diameter>
		<frame_material><![CDATA[Steel]]></frame_material>
		<brake_type><![CDATA[Disk hydraulic]]></brake_type>
	</node>
	<node>
		<sku><![CDATA[214845847]]></sku>
		<category><![CDATA[Electric transport>Electric bicycles]]></category>
		<tags><![CDATA[Ecological]]></tags>
		<title><![CDATA[Електровелосипед Myatu X80M Blue-Black]]></title>
		<price><![CDATA[30132]]></price>
		<color><![CDATA[Blue-Black]]></color>
		<size><![CDATA[14]]></size>
		<images><![CDATA[https://content2.rozetka.com.ua/goods/images/big/24819067.jpg|https://content2.rozetka.com.ua/goods/images/big/24819133.jpg|https://content2.rozetka.com.ua/goods/images/big/24819169.jpg|https://content2.rozetka.com.ua/goods/images/big/24819233.jpg|https://content.rozetka.com.ua/goods/images/big/24819266.jpg]]></images>
		<class><![CDATA[City]]></class>
		<number_of_speeds><![CDATA[]]></number_of_speeds>
		<max_speed><![CDATA[30]]></max_speed>
		<wheel_diameter><![CDATA[20]]></wheel_diameter>
		<frame_material><![CDATA[Steel]]></frame_material>
		<brake_type><![CDATA[Disk hydraulic]]></brake_type>
	</node>
	<node>
		<sku><![CDATA[157275217]]></sku>
		<category><![CDATA[Electric transport>Electric bicycles]]></category>
		<tags><![CDATA[Ecological]]></tags>
		<title><![CDATA[Електровелосипед MAKE 36V 12Ah 500W рама 17"/ 26"]]></title>
		<price><![CDATA[21790]]></price>
		<color><![CDATA[Red]]></color>
		<size><![CDATA[17]]></size>
		<images><![CDATA[https://content.rozetka.com.ua/goods/images/big/106397980.png|https://content1.rozetka.com.ua/goods/images/big/106398067.png|https://content2.rozetka.com.ua/goods/images/big/106398074.png]]></images>
		<class><![CDATA[mountin]]></class>
		<number_of_speeds><![CDATA[]]></number_of_speeds>
		<max_speed><![CDATA[40]]></max_speed>
		<wheel_diameter><![CDATA[26]]></wheel_diameter>
		<frame_material><![CDATA[Aluminum]]></frame_material>
		<brake_type><![CDATA[Disk hydraulic]]></brake_type>
	</node>
	<node>
		<sku><![CDATA[157275455]]></sku>
		<category><![CDATA[Electric transport>Electric bicycles]]></category>
		<tags><![CDATA[Ecological]]></tags>
		<title><![CDATA[Електровелосипед MAKE 36V 12Ah 500W рама 17"/ 26"]]></title>
		<price><![CDATA[21790]]></price>
		<color><![CDATA[Bue]]></color>
		<size><![CDATA[17]]></size>
		<images><![CDATA[https://content.rozetka.com.ua/goods/images/big/106398089.png|https://content2.rozetka.com.ua/goods/images/big/106398098.png|https://content2.rozetka.com.ua/goods/images/big/106398109.png]]></images>
		<class><![CDATA[mountin]]></class>
		<number_of_speeds><![CDATA[]]></number_of_speeds>
		<max_speed><![CDATA[40]]></max_speed>
		<wheel_diameter><![CDATA[26]]></wheel_diameter>
		<frame_material><![CDATA[Aluminum]]></frame_material>
		<brake_type><![CDATA[Disk hydraulic]]></brake_type>
	</node>
	<node>
		<sku><![CDATA[157275539]]></sku>
		<category><![CDATA[Electric transport>Electric bicycles]]></category>
		<tags><![CDATA[Ecological]]></tags>
		<title><![CDATA[Електровелосипед MAKE 36V 12Ah 500W рама 17"/ 26"]]></title>
		<price><![CDATA[21790]]></price>
		<color><![CDATA[Green]]></color>
		<size><![CDATA[17]]></size>
		<images><![CDATA[https://content2.rozetka.com.ua/goods/images/big/106398250.png|https://content1.rozetka.com.ua/goods/images/big/106398276.png|https://content.rozetka.com.ua/goods/images/big/106398283.png]]></images>
		<class><![CDATA[mountin]]></class>
		<number_of_speeds><![CDATA[]]></number_of_speeds>
		<max_speed><![CDATA[40]]></max_speed>
		<wheel_diameter><![CDATA[26]]></wheel_diameter>
		<frame_material><![CDATA[Aluminum]]></frame_material>
		<brake_type><![CDATA[Disk hydraulic]]></brake_type>
	</node>
	<node>
		<sku><![CDATA[157275791]]></sku>
		<category><![CDATA[Electric transport>Electric bicycles]]></category>
		<tags><![CDATA[Ecological]]></tags>
		<title><![CDATA[Електровелосипед MAKE 36V 12Ah 500W рама 17"/ 26"]]></title>
		<price><![CDATA[21790]]></price>
		<color><![CDATA[Whire]]></color>
		<size><![CDATA[17]]></size>
		<images><![CDATA[https://content2.rozetka.com.ua/goods/images/big/106398351.png]]></images>
		<class><![CDATA[mountin]]></class>
		<number_of_speeds><![CDATA[]]></number_of_speeds>
		<max_speed><![CDATA[40]]></max_speed>
		<wheel_diameter><![CDATA[26]]></wheel_diameter>
		<frame_material><![CDATA[Aluminum]]></frame_material>
		<brake_type><![CDATA[Disk hydraulic]]></brake_type>
	</node>
	<node>
		<sku><![CDATA[190032634]]></sku>
		<category><![CDATA[Electric transport>Electric bicycles]]></category>
		<tags><![CDATA[Ecological]]></tags>
		<title><![CDATA[Електровелосипед Zhengbu M8 Black from red]]></title>
		<price><![CDATA[18833]]></price>
		<color><![CDATA[Red]]></color>
		<size><![CDATA[16]]></size>
		<images><![CDATA[https://content2.rozetka.com.ua/goods/images/big/118973418.jpg|https://content2.rozetka.com.ua/goods/images/big/118973450.jpg|https://content.rozetka.com.ua/goods/images/big/118973482.jpg|https://content.rozetka.com.ua/goods/images/big/118973503.jpg|https://content1.rozetka.com.ua/goods/images/big/118973518.jpg|https://content1.rozetka.com.ua/goods/images/big/118973528.jpg]]></images>
		<class><![CDATA[Adalts]]></class>
		<number_of_speeds><![CDATA[]]></number_of_speeds>
		<max_speed><![CDATA[25]]></max_speed>
		<wheel_diameter><![CDATA[26]]></wheel_diameter>
		<frame_material><![CDATA[Aluminum]]></frame_material>
		<brake_type><![CDATA[Disk hydraulic]]></brake_type>
	</node>
	<node>
		<sku><![CDATA[286672493]]></sku>
		<category><![CDATA[Electric transport>Electric bicycles]]></category>
		<tags><![CDATA[Ecological]]></tags>
		<title><![CDATA[Електровелосипед Заря Силач 450W 60V/12AH червоний]]></title>
		<price><![CDATA[22540]]></price>
		<color><![CDATA[Red]]></color>
		<size><![CDATA[16]]></size>
		<images><![CDATA[https://content2.rozetka.com.ua/goods/images/big/173742375.jpg|https://content1.rozetka.com.ua/goods/images/big/173742377.jpg|https://content.rozetka.com.ua/goods/images/big/173742379.jpg|https://content1.rozetka.com.ua/goods/images/big/173742381.jpg]]></images>
		<class><![CDATA[City]]></class>
		<number_of_speeds><![CDATA[]]></number_of_speeds>
		<max_speed><![CDATA[40]]></max_speed>
		<wheel_diameter><![CDATA[26]]></wheel_diameter>
		<frame_material><![CDATA[Aluminum]]></frame_material>
		<brake_type><![CDATA[Disk hydraulic]]></brake_type>
	</node>
</data>
